{
  "title": "Welkom bij schoonheidssalon Helmich",
  "body": "Schoonheidsverzorging is de kunst om de schoonheid van het lichaam te verhogen en/of te behouden.\n<br><br>\nOm dit te bereiken is rust, reiniging en verzorging met goede producten belangrijk voor het lichaam.",
  "image": "/img/banner.png",
  "blocks": [
    {
      "title": "Afspraak maken",
      "link": "https://ergensanders.nl",
      "image": "/img/banner.png"
    },
    {
      "title": "Webshop",
      "link": "https://ergensanders.nl",
      "image": "/img/banner.png"
    },
    {
      "title": "Tarieven",
      "link": "https://ergensanders.nl",
      "image": "/img/banner.png"
    }
  ]
}